everysk_mcp/__init__.py
everysk_mcp/server.py
everysk_mcp/utils.py
everysk_mcp/blueprints/securities.py
everysk_mcp/fields/definitions.py
everysk_mcp/fields/securities.py
everysk_mcp/prompts/templates.py
everysk_mcp/resources/static.py
everysk_mcp/resources/templates.py
everysk_mcp/tests/.gitkeep
everysk_mcp/tools/calculation.py
everysk_mcp/tools/datastore.py
everysk_mcp/tools/file.py
everysk_mcp/tools/portfolio.py
everysk_mcp/tools/report.py
everysk_mcp/tools/report_template.py
everysk_mcp/tools/workflow.py
everysk_mcp/tools/workflow_execution.py
everysk_mcp/tools/workspace.py
everysk_mcp-0.1.74.dist-info/METADATA
everysk_mcp-0.1.74.dist-info/WHEEL
everysk_mcp-0.1.74.dist-info/entry_points.txt
everysk_mcp-0.1.74.dist-info/licenses/LICENSE.txt
everysk_mcp-0.1.74.dist-info/RECORD
