Metadata-Version: 2.4
Name: everysk-mcp
Version: 0.1.74
Summary: Model Context Protocol (MCP) implementation for Everysk.
Project-URL: Homepage, https://everysk.com/
License-Expression: LicenseRef-Proprietary
License-File: LICENSE.txt
Keywords: development,mcp,python
Classifier: Development Status :: 4 - Beta
Classifier: Intended Audience :: End Users/Desktop
Classifier: Operating System :: OS Independent
Classifier: Programming Language :: Python :: 3.12
Classifier: Topic :: Software Development :: Libraries :: Python Modules
Requires-Python: ==3.12.*
Requires-Dist: everysk-lib==1.6.1670
Requires-Dist: mcp[cli]==1.9.3
Requires-Dist: pydantic==2.11.5
Requires-Dist: requests==2.32.4
